{
  "required": true,
  "minVersion": "0.8",
  "package": "io.github.amelonrind.stereopsis.mixin",
  "plugin": "io.github.amelonrind.stereopsis.mixin.ConfigPluginImpl",
  "compatibilityLevel": "JAVA_21",
  "mixins": [
  ],
  "client": [
    "MixinAccessCamera",
    "MixinAccessEntityRenderer",
    "MixinAccessHeldItemRenderer",
    "MixinAccessPostEffectProcessor",
    "MixinChatHud",
    "MixinGameRenderer",
    "MixinHeldItemRenderer",
    "MixinInGameHud",
    "MixinMinecraftClient",
    "MixinPostEffectProcessor",
    "MixinSpectatorHud",
    "MixinSubtitlesHud",
    "devgpupatch.MixinGameRenderer",
    "devgpupatch.MixinVertexBuffer"
  ],
  "injectors": {
    "defaultRequire": 1
  }
}
